{
    "levels": [
        {
            "levelname": "level1",
            "objects": [
                {
                    "filepath": "../GEA2021/Assets/Meshes/player.obj",
                    "positionx": 0,
                    "positiony": -1.7999999523162842,
                    "positionz": -8,
                    "shader": 0,
                    "usingLOD": false
                },
                {
                    "filepath": "../GEA2021/Assets/Meshes/light.obj",
                    "positionx": 3.120039463043213,
                    "positiony": 3,
                    "positionz": -30.30433464050293,
                    "shader": 0,
                    "usingLOD": false
                },
                {
                    "filepath": "../GEA2021/Assets/Meshes/cacodemon2.obj",
                    "positionx": 5,
                    "positiony": 0,
                    "positionz": -7,
                    "shader": 2,
                    "usingLOD": false
                },
                {
                    "filepath": "../GEA2021/Assets/Meshes/cube.obj",
                    "positionx": -1,
                    "positiony": -1,
                    "positionz": -5,
                    "shader": 0,
                    "usingLOD": false
                },
                {
                    "filepath": "../GEA2021/Assets/Meshes/cube.obj",
                    "positionx": -3,
                    "positiony": -1,
                    "positionz": -5,
                    "shader": 0,
                    "usingLOD": false
                },
                {
                    "filepath": "../GEA2021/Assets/Meshes/sphere.obj",
                    "positionx": 14,
                    "positiony": 7,
                    "positionz": -27,
                    "shader": 0,
                    "usingLOD": true
                },
                {
                    "filepath": "../GEA2021/Assets/Meshes/pyramid.obj",
                    "positionx": -1,
                    "positiony": 0.5,
                    "positionz": -5,
                    "shader": 0,
                    "usingLOD": false
                },
                {
                    "filepath": "../GEA2021/Assets/Meshes/suzanne.obj",
                    "positionx": -12,
                    "positiony": 0.5,
                    "positionz": -13,
                    "shader": 2,
                    "usingLOD": true
                },
                {
                    "filepath": "../GEA2021/Assets/Meshes/suzanne.obj",
                    "positionx": 0,
                    "positiony": 0,
                    "positionz": 2.5,
                    "shader": 2,
                    "usingLOD": true
                },
                {
                    "filepath": "../GEA2021/Assets/Meshes/suzanne.obj",
                    "positionx": -8.5,
                    "positiony": 3.5999999046325684,
                    "positionz": -16.899999618530273,
                    "shader": 2,
                    "usingLOD": true
                },
                {
                    "filepath": "../GEA2021/Assets/Meshes/suzanne.obj",
                    "positionx": -4.199999809265137,
                    "positiony": -3.799999952316284,
                    "positionz": -2.200000047683716,
                    "shader": 2,
                    "usingLOD": true
                },
                {
                    "filepath": "../GEA2021/Assets/Meshes/sphere.obj",
                    "positionx": 0,
                    "positiony": 0,
                    "positionz": 0,
                    "shader": 2,
                    "usingLOD": true
                },
                {
                    "filepath": "../GEA2021/Assets/Meshes/pyramid.obj",
                    "positionx": 0,
                    "positiony": 0,
                    "positionz": 0,
                    "shader": 2,
                    "usingLOD": false
                }
            ]
        }
    ]
}
